{
  "_class": "shapePath",
  "booleanOperation": -1,
  "do_objectID": "B5C2322E-40CA-43AD-92FE-F5E48E48B271",
  "edited": true,
  "exportOptions": {
    "_class": "exportOptions",
    "exportFormats": [
    ],
    "includedLayerIds": [
    ],
    "layerOptions": 0,
    "shouldTrim": false
  },
  "frame": {
    "_class": "rect",
    "constrainProportions": false,
    "height": 10,
    "width": 10,
    "x": 5,
    "y": 5
  },
  "isFlippedHorizontal": false,
  "isFlippedVertical": false,
  "isLocked": false,
  "isVisible": true,
  "layerListExpandedType": 0,
  "name": "Path",
  "nameIsFixed": false,
  "path": {
    "_class": "path",
    "isClosed": true,
    "pointRadiusBehaviour": 0,
    "points": [
      {
        "_class": "curvePoint",
        "cornerRadius": 0,
        "curveFrom": "{1, 1}",
        "curveMode": 1,
        "curveTo": "{1, 1}",
        "hasCurveFrom": false,
        "hasCurveTo": false,
        "point": "{1, 1}"
      },
      {
        "_class": "curvePoint",
        "cornerRadius": 0,
        "curveFrom": "{0.67932007928404103, 1}",
        "curveMode": 1,
        "curveTo": "{0.67932007928404103, 1}",
        "do_objectID": "AA0A221C-EECF-42CA-A4FD-CD0FDA6B2161",
        "hasCurveFrom": false,
        "hasCurveTo": false,
        "point": "{0.67932007928404103, 1}"
      },
      {
        "_class": "curvePoint",
        "cornerRadius": 0,
        "curveFrom": "{0.67932007928404103, 0.41230262410541857}",
        "curveMode": 4,
        "curveTo": "{0.67932007928404103, 0.52544587072588878}",
        "do_objectID": "F77F24CD-42D4-42D7-B50C-605E287C553E",
        "hasCurveFrom": true,
        "hasCurveTo": false,
        "point": "{0.67932007928404103, 0.52544587072588878}"
      },
      {
        "_class": "curvePoint",
        "cornerRadius": 0,
        "curveFrom": "{0.34578653372574925, 0.26672725207315673}",
        "curveMode": 2,
        "curveTo": "{0.67727791458946485, 0.26672725207315673}",
        "do_objectID": "DD7DA2A3-08F8-4D9E-8D04-D530BC667824",
        "hasCurveFrom": true,
        "hasCurveTo": true,
        "point": "{0.51270346567361402, 0.26672725207315673}"
      },
      {
        "_class": "curvePoint",
        "cornerRadius": 0,
        "curveFrom": "{0.32031953871103369, 0.51738043848687953}",
        "curveMode": 4,
        "curveTo": "{0.32031953871103369, 0.39003748722026582}",
        "do_objectID": "753EA785-C128-4815-9A91-07CE1335678B",
        "hasCurveFrom": false,
        "hasCurveTo": true,
        "point": "{0.32031953871103369, 0.51738043848687953}"
      },
      {
        "_class": "curvePoint",
        "cornerRadius": 0,
        "curveFrom": "{0.32031953871103369, 1}",
        "curveMode": 1,
        "curveTo": "{0.32031953871103369, 1}",
        "do_objectID": "00CA8FF0-5FEB-4BF8-98A0-D50066E26966",
        "hasCurveFrom": false,
        "hasCurveTo": false,
        "point": "{0.32031953871103369, 1}"
      },
      {
        "_class": "curvePoint",
        "cornerRadius": 0,
        "curveFrom": "{0, 1}",
        "curveMode": 1,
        "curveTo": "{0, 1}",
        "hasCurveFrom": false,
        "hasCurveTo": false,
        "point": "{0, 1}"
      },
      {
        "_class": "curvePoint",
        "cornerRadius": 0,
        "curveFrom": "{0, 0.024196296717028193}",
        "curveMode": 1,
        "curveTo": "{0, 0.024196296717028193}",
        "do_objectID": "66A85CE9-AA0C-49F5-96CF-13C967DEC2C8",
        "hasCurveFrom": false,
        "hasCurveTo": false,
        "point": "{0, 0.024196296717028193}"
      },
      {
        "_class": "curvePoint",
        "cornerRadius": 0,
        "curveFrom": "{0.3074058502012133, 0.024196296717028193}",
        "curveMode": 1,
        "curveTo": "{0.3074058502012133, 0.024196296717028193}",
        "do_objectID": "6DA020D0-0B49-4DF8-A731-104AF83BCA2D",
        "hasCurveFrom": false,
        "hasCurveTo": false,
        "point": "{0.3074058502012133, 0.024196296717028193}"
      },
      {
        "_class": "curvePoint",
        "cornerRadius": 0,
        "curveFrom": "{0.3074058502012133, 0.1576167215721912}",
        "curveMode": 1,
        "curveTo": "{0.3074058502012133, 0.1576167215721912}",
        "do_objectID": "FCEC8E2E-3F4E-49F4-81E0-5D49CB64617E",
        "hasCurveFrom": false,
        "hasCurveTo": false,
        "point": "{0.3074058502012133, 0.1576167215721912}"
      },
      {
        "_class": "curvePoint",
        "cornerRadius": 0,
        "curveFrom": "{0.35461589284641726, 0.080881517664432537}",
        "curveMode": 4,
        "curveTo": "{0.3118505615952909, 0.1576167215721912}",
        "do_objectID": "A48BF4EC-18A8-4852-97FC-4F928D0E6080",
        "hasCurveFrom": true,
        "hasCurveTo": false,
        "point": "{0.3118505615952909, 0.1576167215721912}"
      },
      {
        "_class": "curvePoint",
        "cornerRadius": 0,
        "curveFrom": "{0.93999639617995068, 0}",
        "curveMode": 3,
        "curveTo": "{0.45924680160970621, 0}",
        "do_objectID": "3E2B1890-62B0-4865-B146-89C75B37F209",
        "hasCurveFrom": true,
        "hasCurveTo": true,
        "point": "{0.61523214607483934, 0}"
      },
      {
        "_class": "curvePoint",
        "cornerRadius": 0,
        "curveFrom": "{1, 0.46484153129614886}",
        "curveMode": 4,
        "curveTo": "{1, 0.20203339770532763}",
        "do_objectID": "3F362241-93D4-4B84-A3F5-C056CE718043",
        "hasCurveFrom": false,
        "hasCurveTo": true,
        "point": "{1, 0.46484153129614886}"
      },
      {
        "_class": "curvePoint",
        "cornerRadius": 0,
        "curveFrom": "{1, 1}",
        "curveMode": 1,
        "curveTo": "{1, 1}",
        "hasCurveFrom": false,
        "hasCurveTo": false,
        "point": "{1, 1}"
      }
    ]
  },
  "resizingConstraint": 63,
  "resizingType": 0,
  "rotation": 0,
  "shouldBreakMaskChain": false
}